README.md
setup.py
datapunt_django_snapshot.egg-info/PKG-INFO
datapunt_django_snapshot.egg-info/SOURCES.txt
datapunt_django_snapshot.egg-info/dependency_links.txt
datapunt_django_snapshot.egg-info/requires.txt
datapunt_django_snapshot.egg-info/top_level.txt
snapshot/__init__.py
snapshot/importer.py
snapshot/managers.py
snapshot/models.py
snapshot/scraper.py