Metadata-Version: 1.0
Name: datapunt-django-snapshot
Version: 0.1.0
Summary: A collection of classes to easily scrape/import APIs
Home-page: UNKNOWN
Author: Datapunt Amsterdam
Author-email: datapunt@amsterdam.nl
License: Mozilla Public License 2.0
Platform: UNKNOWN
